curryreader.py
curryreader-0.1.2.dist-info/METADATA
curryreader-0.1.2.dist-info/WHEEL
curryreader-0.1.2.dist-info/licenses/LICENSE
curryreader-0.1.2.dist-info/RECORD
