Metadata-Version: 2.4
Name: curryreader
Version: 0.1.2
Summary: File reader for Compumedics Neuroscan data formats (.cdt, .dat).
Project-URL: Bug Tracker, https://github.com/mne-tools/curry-python-reader/issues/
Project-URL: Documentation, https://github.com/mne-tools/curry-python-reader/blob/main/README.md
Project-URL: Download, https://pypi.org/project/curryreader/#files
Project-URL: Forum, https://mne.discourse.group/
Project-URL: Source Code, https://github.com/mne-tools/curry-python-reader/
Author-email: Fernando Gasca <fgasca@neuroscan.com>
Maintainer-email: Dan McCloy <dan@mccloy.info>
License: BSD-3-Clause
License-File: LICENSE
Keywords: EEG,MEG,brain,neuroimaging,neuroscience
Classifier: License :: OSI Approved
Classifier: Operating System :: OS Independent
Classifier: Programming Language :: Python :: 3
Classifier: Topic :: Scientific/Engineering
Classifier: Topic :: Software Development
Requires-Python: >=3.7
Requires-Dist: certifi>=2020.6.20
Requires-Dist: cycler>=0.10.0
Requires-Dist: kiwisolver>=1.2.0
Requires-Dist: matplotlib>=3.3.2
Requires-Dist: numpy>=1.19.2
Requires-Dist: pillow>=8.0.1
Requires-Dist: pip>=21.0.1
Requires-Dist: pyparsing>=2.4.7
Requires-Dist: python-dateutil>=2.8.1
Requires-Dist: setuptools>=50.3.2
Requires-Dist: six>=1.15.0
